gif_steganography/__init__.py
gif_steganography/cli.py
gif_steganography/common.py
gif_steganography/decode.py
gif_steganography/encode.py
gif_steganography/lib/__init__.py
gif_steganography/lib/_compression.py
gif_steganography/lib/_ecc.py
gif_steganography/lib/_encryption.py
gif_steganography/lib/_gif.py
gif_steganography/modes/__init__.py
gif_steganography/modes/_cshift.py
gif_steganography/modes/_lsb.py
gif_steganography-0.1.1.dist-info/entry_points.txt
gif_steganography-0.1.1.dist-info/WHEEL
gif_steganography-0.1.1.dist-info/METADATA
gif_steganography-0.1.1.dist-info/licenses/LICENSE
gif_steganography-0.1.1.dist-info/RECORD
