Metadata-Version: 2.1
Name: gif-steganography
Version: 0.1.1
Summary: A Python GIF steganography library supporting encryption to embed and extract secure messages within GIF images.
License: MIT
Author-email: nebmit <76664673+nebmit@users.noreply.github.com>
Requires-Python: >=3.10
Requires-Dist: Pillow==10.3.0
Requires-Dist: cryptography
Requires-Dist: numpy==2.2.4
Requires-Dist: reedsolo==1.7.0
